foundation_stereo/__init__.py
foundation_stereo/build.py
foundation_stereo/test.py
foundation_stereo/transforms.py
foundation_stereo/vis_utils.py
foundation_stereo/models/__init__.py
foundation_stereo/models/foundation_stereo.py
foundation_stereo/models/depth_anything/blocks.py
foundation_stereo/models/depth_anything/dpt.py
foundation_stereo/models/depth_anything/util/transform.py
foundation_stereo/models/libs/extractor.py
foundation_stereo/models/libs/geometry.py
foundation_stereo/models/libs/submodule.py
foundation_stereo/models/libs/update.py
foundation_stereo/models/libs/utils.py
foundation_stereo-0.0.2.dist-info/LICENSE
foundation_stereo-0.0.2.dist-info/METADATA
foundation_stereo-0.0.2.dist-info/WHEEL
foundation_stereo-0.0.2.dist-info/top_level.txt
foundation_stereo-0.0.2.dist-info/zip-safe
foundation_stereo-0.0.2.dist-info/RECORD
